./.env.example
./.gitignore
./ANALISE_INCONSISTENCIAS.md
./ATUALIZAÇÃO_UV_RESUMO.md
./AUDITORIA_PROJETO.md
./AVALIACAO_PROJETO.md
./COMANDOS_UV.md
./COMECE_AQUI.md
./COMO_USAR_UV.md
./CONFIGURACAO_ENV.txt
./ESTRUTURA.md
./IMPLEMENTACAO_CONCLUIDA.md
./IMPLEMENTATION_V2_SUMMARY.md
./INCONSISTENCIAS_CORRIGIDAS.md
./INDICE.md
./LICENSE
./MANIFEST.in
./MAPA_RECURSOS.md
./PAINEL_ATUALIZACAO.md
./PKG-INFO
./QUICKSTART_UV.md
./QUICKSTART_V2.md
./README.md
./README_ATUALIZACAO.txt
./RELATORIO_CORRECOES.md
./RESUMO_ATUALIZAÇÃO.py
./ROADMAP_CREWAI_COMPARISON.md
./STATUS_AMBIENTE.txt
./SUMARIO_EXECUTIVO.md
./SUPORTE_DUAL_PIP_UV.md
./TESTING_V2.md
./UV_VS_PIP_REFERENCIA.md
./check_setup.py
./config.py
./config_template.json
./mangaba_agent.py
./mangaba_ai.py
./pyproject.toml
./pytest.ini
./requirements-test.txt
./requirements.txt
./setup.py
./test_basic.py
./test_correcoes.py
./test_setup.py
./uv-profile.ps1
./uv.bat
./uv.lock
./docs/CHANGELOG.md
./docs/CI_CD_UV.md
./docs/CONTRIBUICAO.md
./docs/CURSO_BASICO.md
./docs/FAQ.md
./docs/GLOSSARIO.md
./docs/INDICE_UV.md
./docs/MELHORES_PRATICAS.md
./docs/MIGRACAO_PIP_UV.md
./docs/PROTOCOLS.md
./docs/README.md
./docs/SCRIPTS.md
./docs/SETUP.md
./docs/UV_SETUP.md
./docs/WIKI.md
./examples/administration_example.py
./examples/api_integration_example.py
./examples/basic_example.py
./examples/crew_example.py
./examples/document_analysis_example.py
./examples/finance_example.py
./examples/legal_example.py
./examples/marketing_example.py
./examples/medical_example.py
./examples/ml_analytics_example.py
./examples/task_automation_example.py
./examples/text_analysis_example.py
./examples/translation_example.py
./mangaba/__init__.py
./mangaba/core/__init__.py
./mangaba/core/agent.py
./mangaba/core/crew.py
./mangaba/core/task.py
./mangaba/tools/__init__.py
./mangaba/tools/base.py
./mangaba/tools/file_tools.py
./mangaba/tools/web_search.py
./protocols/__init__.py
./protocols/a2a.py
./protocols/mcp.py
./scripts/README.md
mangaba-2.0.0.dist-info/METADATA
mangaba-2.0.0.dist-info/WHEEL
mangaba-2.0.0.dist-info/licenses/LICENSE
mangaba-2.0.0.dist-info/RECORD
