Metadata-Version: 2.4
Name: mangaba
Version: 2.0.0
Summary: Framework de Agentes IA com Multi-Agent Orchestration, Protocolos A2A e MCP
Project-URL: Homepage, https://github.com/mangaba-ai/mangaba-ai
Project-URL: Bug Reports, https://github.com/mangaba-ai/mangaba-ai/issues
Project-URL: Source, https://github.com/mangaba-ai/mangaba-ai
Project-URL: Documentation, https://github.com/mangaba-ai/mangaba-ai#readme
Author-email: Mangaba AI Team <contato@mangaba.ai>
License: MIT
License-File: LICENSE
Keywords: agent,ai,artificial-intelligence,chatbot,gemini,google,protocol
Classifier: Development Status :: 4 - Beta
Classifier: Intended Audience :: Developers
Classifier: License :: OSI Approved :: MIT License
Classifier: Operating System :: OS Independent
Classifier: Programming Language :: Python :: 3
Classifier: Programming Language :: Python :: 3.9
Classifier: Programming Language :: Python :: 3.10
Classifier: Programming Language :: Python :: 3.11
Classifier: Programming Language :: Python :: 3.12
Classifier: Programming Language :: Python :: 3.13
Classifier: Topic :: Scientific/Engineering :: Artificial Intelligence
Classifier: Topic :: Software Development :: Libraries :: Python Modules
Requires-Python: >=3.9
Requires-Dist: google-generativeai>=0.3.0
Requires-Dist: loguru>=0.6.0
Requires-Dist: pydantic>=1.8.0
Requires-Dist: python-dotenv>=0.19.0
Requires-Dist: requests>=2.25.0
Requires-Dist: websockets>=10.0
Provides-Extra: dev
Requires-Dist: black>=23.0.0; extra == 'dev'
Requires-Dist: coverage>=7.2.0; extra == 'dev'
Requires-Dist: factory-boy>=3.3.0; extra == 'dev'
Requires-Dist: faker>=19.0.0; extra == 'dev'
Requires-Dist: flake8>=6.0.0; extra == 'dev'
Requires-Dist: freezegun>=1.2.2; extra == 'dev'
Requires-Dist: isort>=5.12.0; extra == 'dev'
Requires-Dist: memory-profiler>=0.61.0; extra == 'dev'
Requires-Dist: mypy>=1.5.0; extra == 'dev'
Requires-Dist: parameterized>=0.9.0; extra == 'dev'
Requires-Dist: pytest-asyncio>=0.21.1; extra == 'dev'
Requires-Dist: pytest-benchmark>=4.0.0; extra == 'dev'
Requires-Dist: pytest-cov>=4.1.0; extra == 'dev'
Requires-Dist: pytest-github-actions-annotate-failures>=0.2.0; extra == 'dev'
Requires-Dist: pytest-html>=3.2.0; extra == 'dev'
Requires-Dist: pytest-json-report>=1.5.0; extra == 'dev'
Requires-Dist: pytest-mock>=3.11.1; extra == 'dev'
Requires-Dist: pytest-xdist>=3.3.1; extra == 'dev'
Requires-Dist: pytest>=7.4.0; extra == 'dev'
Requires-Dist: responses>=0.23.0; extra == 'dev'
Provides-Extra: test
Requires-Dist: coverage>=7.2.0; extra == 'test'
Requires-Dist: pytest-asyncio>=0.21.1; extra == 'test'
Requires-Dist: pytest-cov>=4.1.0; extra == 'test'
Requires-Dist: pytest-mock>=3.11.1; extra == 'test'
Requires-Dist: pytest-xdist>=3.3.1; extra == 'test'
Requires-Dist: pytest>=7.4.0; extra == 'test'
Provides-Extra: tools
Requires-Dist: duckduckgo-search>=3.9.0; extra == 'tools'
